{"id":"14216","nombre":"PLAN DE MEJORAMIENTO DE RIEGO EN SIERRA Y SELVA (PLAN MERISS)","tipo":"Organismo público","periodo":"","total":0,"clave":0,"regimenes":[],"organigrama":[],"autoridades":[{"nombre":"Gonzales Rodriguez Leonidas Richard","cargo":"DIRECTOR EJECUTIVO","email":"","telefono":"","url":"https://www.gob.pe/institucion/planmeriss/funcionarios/192622-gonzales-rodriguez-leonidas-richard","entidad":"PLAN DE MEJORAMIENTO DE RIEGO EN SIERRA Y SELVA (PLAN MERISS)","institucion":"PLAN DE MEJORAMIENTO DE RIEGO EN SIERRA Y SELVA (PLAN MERISS)"},{"nombre":"Vilma Gladis Salazar Muñiz","cargo":"JEFE DE UNIDAD PLANIFICACION, PRESUPUESTO Y MODERNIZACION","email":"gsalazar@meriss.gob.pe","telefono":"084-232639","url":"https://www.gob.pe/institucion/planmeriss/funcionarios/60518-vilma-gladis-salazar-muniz","entidad":"PLAN DE MEJORAMIENTO DE RIEGO EN SIERRA Y SELVA (PLAN MERISS)","institucion":"PLAN DE MEJORAMIENTO DE RIEGO EN SIERRA Y SELVA (PLAN MERISS)"},{"nombre":"Romulo Edilberto, Gallegos Ordoñez","cargo":"DIRECTOR DE ESTUDIOS","email":"","telefono":"","url":"https://www.gob.pe/institucion/planmeriss/funcionarios/192626-romulo-edilberto-gallegos-ordonez","entidad":"PLAN DE MEJORAMIENTO DE RIEGO EN SIERRA Y SELVA (PLAN MERISS)","institucion":"PLAN DE MEJORAMIENTO DE RIEGO EN SIERRA Y SELVA (PLAN MERISS)"},{"nombre":"Oscar Milla Noblega","cargo":"DIRECTOR DE SUPERVISIÓN, LIQUIDACIÓN Y TRANSFERENCIA","email":"omilla@meriss.gob.pe","telefono":"084-232639","url":"https://www.gob.pe/institucion/planmeriss/funcionarios/60554-oscar-milla-noblega","entidad":"PLAN DE MEJORAMIENTO DE RIEGO EN SIERRA Y SELVA (PLAN MERISS)","institucion":"PLAN DE MEJORAMIENTO DE RIEGO EN SIERRA Y SELVA (PLAN MERISS)"}],"cobertura_parcial":false,"nota_cobertura":"","dependencias":[]}