{"id":"14226","nombre":"SERVICIO DE ADMINISTRACION TRIBUTARIA DE CAJAMARCA (SAT CAJAMARCA)","tipo":"Organismo público","periodo":"","total":0,"clave":0,"regimenes":[],"autoridades":[{"nombre":"Pajares Rabanal, Cristian Paul","cargo":"Jefe","email":"cpajares@satcajamarca.gob.pe","telefono":"976757021","url":"https://www.gob.pe/institucion/satcajamarca/funcionarios/115156-pajares-rabanal-cristian-paul","entidad":"SERVICIO DE ADMINISTRACION TRIBUTARIA DE CAJAMARCA (SAT CAJAMARCA)","institucion":"SERVICIO DE ADMINISTRACION TRIBUTARIA DE CAJAMARCA (SAT CAJAMARCA)"},{"nombre":"Karol Beatriz Cepeda Saenz","cargo":"Gerente de Administración","email":"karol.cepeda@satcajamarca.gob.pe","telefono":"965 434 372","url":"https://www.gob.pe/institucion/satcajamarca/funcionarios/215720-karol-beatriz-cepeda-saenz","entidad":"SERVICIO DE ADMINISTRACION TRIBUTARIA DE CAJAMARCA (SAT CAJAMARCA)","institucion":"SERVICIO DE ADMINISTRACION TRIBUTARIA DE CAJAMARCA (SAT CAJAMARCA)"},{"nombre":"Aquino Sandoval José Armando","cargo":"Asesor Jurídico","email":"jaquino@satcajamarca.gob.pe","telefono":"990988451","url":"https://www.gob.pe/institucion/satcajamarca/funcionarios/115159-aquino-sandoval-jose-armando","entidad":"SERVICIO DE ADMINISTRACION TRIBUTARIA DE CAJAMARCA (SAT CAJAMARCA)","institucion":"SERVICIO DE ADMINISTRACION TRIBUTARIA DE CAJAMARCA (SAT CAJAMARCA)"},{"nombre":"Edwin Marcelo Vásquez Chávez","cargo":"Gerente de Operaciones","email":"","telefono":"972 239 985","url":"https://www.gob.pe/institucion/satcajamarca/funcionarios/221868-edwin-marcelo-vasquez-chavez","entidad":"SERVICIO DE ADMINISTRACION TRIBUTARIA DE CAJAMARCA (SAT CAJAMARCA)","institucion":"SERVICIO DE ADMINISTRACION TRIBUTARIA DE CAJAMARCA (SAT CAJAMARCA)"},{"nombre":"César Minchán Quiroz","cargo":"Jefe Oficina de Informática","email":"c_minchan@satcajamarca.gob.pe","telefono":"976686810","url":"https://www.gob.pe/institucion/satcajamarca/funcionarios/175235-cesar-minchan-quiroz","entidad":"SERVICIO DE ADMINISTRACION TRIBUTARIA DE CAJAMARCA (SAT CAJAMARCA)","institucion":"SERVICIO DE ADMINISTRACION TRIBUTARIA DE CAJAMARCA (SAT CAJAMARCA)"}],"cobertura_parcial":false,"nota_cobertura":"","dependencias":[]}