{"id":"14239","nombre":"UNIDAD DE GESTIÓN EDUCATIVA LOCAL N.º 05 (UGEL 05)","tipo":"Educación","periodo":"6/2026","total":1,"clave":0,"regimenes":[["CAS",1]],"autoridades":[{"nombre":"Beleny Lis Inocencio Silva","cargo":"Directora (e) de la UGEL 05","email":"binocencio@ugel05.gob.pe","telefono":"(01) 459-1135","url":"https://www.gob.pe/institucion/ugel05/funcionarios/254128-beleny-lis-inocencio-silva","entidad":"UNIDAD DE GESTIÓN EDUCATIVA LOCAL N.º 05 (UGEL 05)","institucion":"UNIDAD DE GESTIÓN EDUCATIVA LOCAL N.º 05 (UGEL 05)"},{"nombre":"Beleny Lis Inocencio Silva","cargo":"Jefe del Área de Gestión de la Educación Básica Regular y Especial","email":"binocencio@ugel05.gob.pe","telefono":"(01) 459890","url":"https://www.gob.pe/institucion/ugel05/funcionarios/138575-beleny-lis-inocencio-silva","entidad":"UNIDAD DE GESTIÓN EDUCATIVA LOCAL N.º 05 (UGEL 05)","institucion":"UNIDAD DE GESTIÓN EDUCATIVA LOCAL N.º 05 (UGEL 05)"},{"nombre":"Zoila Margot Valverde Gonzales","cargo":"Jefe del Área de Gestión de la Educativa Básica Alternativa y Técnico Productiva","email":"zvalverde@ugel05.gob.pe","telefono":"(01) 459-1135","url":"https://www.gob.pe/institucion/ugel05/funcionarios/138733-zoila-margot-valverde-gonzales","entidad":"UNIDAD DE GESTIÓN EDUCATIVA LOCAL N.º 05 (UGEL 05)","institucion":"UNIDAD DE GESTIÓN EDUCATIVA LOCAL N.º 05 (UGEL 05)"},{"nombre":"Emérita Dina Brio Calizaya","cargo":"Jefa del Área de Supervisión y Gestión del Servicio Educativo","email":"ebrio@ugel05.gob.pe","telefono":"(01) 4598490","url":"https://www.gob.pe/institucion/ugel05/funcionarios/186399-emerita-dina-brio-calizaya","entidad":"UNIDAD DE GESTIÓN EDUCATIVA LOCAL N.º 05 (UGEL 05)","institucion":"UNIDAD DE GESTIÓN EDUCATIVA LOCAL N.º 05 (UGEL 05)"},{"nombre":"Rommy Giovanna Jara Castro","cargo":"Jefa del Área de Asesoría Jurídica","email":"jefaturaaj@ugel05.gob.pe","telefono":"","url":"https://www.gob.pe/institucion/ugel05/funcionarios/15707-rommy-giovanna-jara-castro","entidad":"UNIDAD DE GESTIÓN EDUCATIVA LOCAL N.º 05 (UGEL 05)","institucion":"UNIDAD DE GESTIÓN EDUCATIVA LOCAL N.º 05 (UGEL 05)"},{"nombre":"Cecilia Magaly Llanos Farias","cargo":"Jefa del área de Recursos Humanos","email":"cllanos@ugel05.gob.pe","telefono":"014591135","url":"https://www.gob.pe/institucion/ugel05/funcionarios/127120-cecilia-magaly-llanos-farias","entidad":"UNIDAD DE GESTIÓN EDUCATIVA LOCAL N.º 05 (UGEL 05)","institucion":"UNIDAD DE GESTIÓN EDUCATIVA LOCAL N.º 05 (UGEL 05)"},{"nombre":"Gloria Marilú Benites Zapana De Lezama","cargo":"Jefa del área de Planificación y Presupuesto","email":"jefatura.app@ugel05.gob.pe","telefono":"(01) 4652033","url":"https://www.gob.pe/institucion/ugel05/funcionarios/130862-gloria-marilu-benites-zapana-de-lezama","entidad":"UNIDAD DE GESTIÓN EDUCATIVA LOCAL N.º 05 (UGEL 05)","institucion":"UNIDAD DE GESTIÓN EDUCATIVA LOCAL N.º 05 (UGEL 05)"},{"nombre":"Eddy Americo Catacora Alatrista","cargo":"Director del Sistema Administrativo II del Área de Administración","email":"ecatacora@ugel05.gob.pe","telefono":"(01) 4591135","url":"https://www.gob.pe/institucion/ugel05/funcionarios/186163-eddy-americo-catacora-alatrista","entidad":"UNIDAD DE GESTIÓN EDUCATIVA LOCAL N.º 05 (UGEL 05)","institucion":"UNIDAD DE GESTIÓN EDUCATIVA LOCAL N.º 05 (UGEL 05)"},{"nombre":"Yudyth Rosario Hurtado Sandoval","cargo":"Jefa del Órgano de Control Institucional","email":"yhurtado@ugel05.gob.pe","telefono":"(511) 459-8490","url":"https://www.gob.pe/institucion/ugel05/funcionarios/212601-yudyth-rosario-hurtado-sandoval","entidad":"UNIDAD DE GESTIÓN EDUCATIVA LOCAL N.º 05 (UGEL 05)","institucion":"UNIDAD DE GESTIÓN EDUCATIVA LOCAL N.º 05 (UGEL 05)"}],"cobertura_parcial":true,"nota_cobertura":"Esta entidad publica en el PTE solo su planilla CAS (administrativa). No figuran docentes nombrados ni autoridades (rector/vicerrectores), que van por el régimen universitario.","dependencias":[{"dependencia":"AGEBRE","n":1,"clave":0,"personas":[{"nombre":"ROSALES SANCHEZ, MARITZA","cargo":"PROFESIONA PEDAGOGICO /AGEBRE","nivel":"Profesional/Apoyo","regimen":"CAS","total":"5364.19","url":"https://www.transparencia.gob.pe/personal/pte_transparencia_personal.aspx?id_entidad=14239&in_anno_consulta=2026&ch_mes_consulta=06&vc_nombre_funcionario=&vc_dni_funcionario=&ch_tipo_regimen=1&id_tema=32&Ver=&pag=1"}]}]}